search_ai/__init__.py
search_ai/extractor.py
search_ai/filters.py
search_ai/parse.py
search_ai/proxy.py
search_ai/search_result.py
search_ai/searcher.py
search_ai/utils.py
search_ai_core-2.0.4.dist-info/licenses/LICENSE
search_ai_core-2.0.4.dist-info/METADATA
search_ai_core-2.0.4.dist-info/WHEEL
search_ai_core-2.0.4.dist-info/top_level.txt
search_ai_core-2.0.4.dist-info/RECORD
