Metadata-Version: 2.4
Name: search-ai-core
Version: 2.0.4
Summary: Search the web with advanced filters and LLM-friendly output formats!
Author: Jacob Padilla
License: MIT
Project-URL: Homepage, https://github.com/jpjacobpadilla/SearchAI
Keywords: python,search,markdown,search-engine,data,ai,web-crawler,llm
Requires-Python: >=3.10
License-File: LICENSE
Requires-Dist: curl-cffi>=0.13.0
Requires-Dist: html2text>=2025.4.15
Requires-Dist: lxml>=5.4.0
Requires-Dist: nest-asyncio>=1.6.0
Requires-Dist: playwright>=1.52.0
Requires-Dist: publicsuffix2>=2.20191221
Requires-Dist: pydantic>=2.11.5
Requires-Dist: tenacity>=9.1.2
Dynamic: license-file
